deppth2/__init__.py
deppth2/__main__.py
deppth2/cli.py
deppth2/compression.py
deppth2/deppth2.py
deppth2/entries.py
deppth2/sggpio.py
deppth2/texpacking.py
deppth2/utils.py
deppth2/texconv/texconv.exe
deppth2-0.1.6.2.dist-info/licenses/LICENSE
deppth2-0.1.6.2.dist-info/METADATA
deppth2-0.1.6.2.dist-info/WHEEL
deppth2-0.1.6.2.dist-info/entry_points.txt
deppth2-0.1.6.2.dist-info/top_level.txt
deppth2-0.1.6.2.dist-info/RECORD
