Metadata-Version: 2.4
Name: deppth2
Version: 0.1.6.2
Summary: Decompress, Extract, and Pack for Pyre, Transistor, Hades, and Hades 2
Home-page: 
Author: SGG Modding
Author-email: xiaoxiao921@hotmail.fr
License-File: LICENSE
Requires-Dist: pillow
Requires-Dist: lz4
Dynamic: author
Dynamic: author-email
Dynamic: description
Dynamic: description-content-type
Dynamic: license-file
Dynamic: requires-dist
Dynamic: summary
